fastapi_user_limiter/__init__.py
fastapi_user_limiter/limiter.py
fastapi_user_limiter-1.3.0.dist-info/METADATA
fastapi_user_limiter-1.3.0.dist-info/WHEEL
fastapi_user_limiter-1.3.0.dist-info/top_level.txt
fastapi_user_limiter-1.3.0.dist-info/RECORD
