Metadata-Version: 2.1
Name: fastapi_user_limiter
Version: 1.3.0
Summary: Rate-limiter for FastAPI with the possibility of user-based rate limits
Author-email: Ramtin Yazdanian <ramtin.yazdanian@epfl.ch>
Project-URL: Homepage, https://github.com/epflgraph/fastapi-user-limiter
Project-URL: Bug Tracker, https://github.com/epflgraph/fastapi-user-limiter/issues
Classifier: Programming Language :: Python :: 3
Classifier: License :: OSI Approved :: MIT License
Classifier: Operating System :: OS Independent
Requires-Python: >=3.11
Requires-Dist: fastapi[all]
Requires-Dist: redis
